beam/__init__.py
beam/__main__.py
beam/cli.py
beam_clipboard-0.2.0.dist-info/licenses/LICENSE
beam_clipboard-0.2.0.dist-info/METADATA
beam_clipboard-0.2.0.dist-info/WHEEL
beam_clipboard-0.2.0.dist-info/entry_points.txt
beam_clipboard-0.2.0.dist-info/top_level.txt
beam_clipboard-0.2.0.dist-info/RECORD
